azure/mgmt/recoveryservicesbackup/passivestamp/__init__.py
azure/mgmt/recoveryservicesbackup/passivestamp/_configuration.py
azure/mgmt/recoveryservicesbackup/passivestamp/_patch.py
azure/mgmt/recoveryservicesbackup/passivestamp/_recovery_services_backup_passive_client.py
azure/mgmt/recoveryservicesbackup/passivestamp/_version.py
azure/mgmt/recoveryservicesbackup/passivestamp/py.typed
azure/mgmt/recoveryservicesbackup/passivestamp/_utils/__init__.py
azure/mgmt/recoveryservicesbackup/passivestamp/_utils/serialization.py
azure/mgmt/recoveryservicesbackup/passivestamp/aio/__init__.py
azure/mgmt/recoveryservicesbackup/passivestamp/aio/_configuration.py
azure/mgmt/recoveryservicesbackup/passivestamp/aio/_patch.py
azure/mgmt/recoveryservicesbackup/passivestamp/aio/_recovery_services_backup_passive_client.py
azure/mgmt/recoveryservicesbackup/passivestamp/aio/operations/__init__.py
azure/mgmt/recoveryservicesbackup/passivestamp/aio/operations/_aad_properties_operations.py
azure/mgmt/recoveryservicesbackup/passivestamp/aio/operations/_backup_crr_job_details_operations.py
azure/mgmt/recoveryservicesbackup/passivestamp/aio/operations/_backup_crr_jobs_operations.py
azure/mgmt/recoveryservicesbackup/passivestamp/aio/operations/_backup_protected_items_crr_operations.py
azure/mgmt/recoveryservicesbackup/passivestamp/aio/operations/_backup_resource_storage_configs_operations.py
azure/mgmt/recoveryservicesbackup/passivestamp/aio/operations/_backup_usage_summaries_crr_operations.py
azure/mgmt/recoveryservicesbackup/passivestamp/aio/operations/_cross_region_restore_operations.py
azure/mgmt/recoveryservicesbackup/passivestamp/aio/operations/_crr_operation_results_operations.py
azure/mgmt/recoveryservicesbackup/passivestamp/aio/operations/_crr_operation_status_operations.py
azure/mgmt/recoveryservicesbackup/passivestamp/aio/operations/_patch.py
azure/mgmt/recoveryservicesbackup/passivestamp/aio/operations/_recovery_points_crr_operations.py
azure_mgmt_recoveryservicesbackup_passivestamp-1.0.0b1.dist-info/licenses/LICENSE
azure_mgmt_recoveryservicesbackup_passivestamp-1.0.0b1.dist-info/METADATA
azure_mgmt_recoveryservicesbackup_passivestamp-1.0.0b1.dist-info/WHEEL
azure_mgmt_recoveryservicesbackup_passivestamp-1.0.0b1.dist-info/top_level.txt
azure_mgmt_recoveryservicesbackup_passivestamp-1.0.0b1.dist-info/RECORD
